qbd/.python-version
qbd/__init__.py
qbd/qbd.py
qbd-0.1.2.post5.dist-info/METADATA
qbd-0.1.2.post5.dist-info/WHEEL
qbd-0.1.2.post5.dist-info/entry_points.txt
qbd-0.1.2.post5.dist-info/licenses/LICENSE
qbd-0.1.2.post5.dist-info/licenses/LICENSE.LESSER
qbd-0.1.2.post5.dist-info/RECORD
