Metadata-Version: 2.4
Name: qbd
Version: 0.1.2.post5
Summary: Creates data cubes from FITS-file image data.
Project-URL: Homepage, https://qbd.lennartheino.de
Project-URL: Issues, https://github.com/idia-astro/qbd/issues
Author: L. Heino
License-Expression: GPL-3.0-or-later
License-File: LICENSE
License-File: LICENSE.LESSER
Classifier: Operating System :: OS Independent
Classifier: Programming Language :: Python :: 3
Requires-Python: >3.9
Requires-Dist: astropy>6.0.0
Requires-Dist: click>8.0.0
Requires-Dist: numpy>=1.23.2
Requires-Dist: rich>12.0.0
